binstar_client/__about__.py
binstar_client/__init__.py
binstar_client/deprecations.py
binstar_client/errors.py
binstar_client/plugins.py
binstar_client/pprintb.py
binstar_client/requests_ext.py
binstar_client/commands/__init__.py
binstar_client/commands/authorizations.py
binstar_client/commands/channel.py
binstar_client/commands/config.py
binstar_client/commands/copy.py
binstar_client/commands/download.py
binstar_client/commands/groups.py
binstar_client/commands/login.py
binstar_client/commands/logout.py
binstar_client/commands/move.py
binstar_client/commands/notebook.py
binstar_client/commands/package.py
binstar_client/commands/remove.py
binstar_client/commands/search.py
binstar_client/commands/show.py
binstar_client/commands/update.py
binstar_client/commands/upload.py
binstar_client/commands/whoami.py
binstar_client/inspect_package/__init__.py
binstar_client/inspect_package/conda.py
binstar_client/inspect_package/conda_installer.py
binstar_client/inspect_package/env.py
binstar_client/inspect_package/ipynb.py
binstar_client/inspect_package/pypi.py
binstar_client/inspect_package/r.py
binstar_client/inspect_package/uitls.py
binstar_client/mixins/__init__.py
binstar_client/mixins/channels.py
binstar_client/mixins/organizations.py
binstar_client/mixins/package.py
binstar_client/scripts/__init__.py
binstar_client/scripts/cli.py
binstar_client/utils/__init__.py
binstar_client/utils/appdirs.py
binstar_client/utils/conda.py
binstar_client/utils/config.py
binstar_client/utils/detect.py
binstar_client/utils/handlers.py
binstar_client/utils/http_codes.py
binstar_client/utils/logging_utils.py
binstar_client/utils/multipart_uploader.py
binstar_client/utils/paths.py
binstar_client/utils/pprint.py
binstar_client/utils/spec.py
binstar_client/utils/tables.py
binstar_client/utils/yaml.py
binstar_client/utils/notebook/__init__.py
binstar_client/utils/notebook/data_uri.py
binstar_client/utils/notebook/downloader.py
binstar_client/utils/notebook/inflection.py
anaconda_cli-1.13.0.dist-info/LICENSE.md
anaconda_cli-1.13.0.dist-info/METADATA
anaconda_cli-1.13.0.dist-info/WHEEL
anaconda_cli-1.13.0.dist-info/entry_points.txt
anaconda_cli-1.13.0.dist-info/top_level.txt
anaconda_cli-1.13.0.dist-info/RECORD
